{
  "kind": "collectionType",
  "collectionName": "orders",
  "info": {
    "singularName": "order",
    "pluralName": "orders",
    "displayName": "Order",
    "description": ""
  },
  "options": {
    "draftAndPublish": false
  },
  "pluginOptions": {},
  "attributes": {
    "Bestellnummer": {
      "type": "uid"
    },
    "payment": {
      "type": "relation",
      "relation": "oneToOne",
      "target": "api::payment.payment"
    },
    "cart": {
      "type": "relation",
      "relation": "oneToOne",
      "target": "api::cart.cart",
      "inversedBy": "order"
    },
    "delivery": {
      "type": "relation",
      "relation": "oneToOne",
      "target": "api::delivery.delivery"
    },
    "address": {
      "type": "text"
    },
    "invoice": {
      "type": "relation",
      "relation": "oneToOne",
      "target": "api::invoice.invoice",
      "mappedBy": "order"
    },
    "sent": {
      "type": "boolean",
      "default": false
    },
    "total": {
      "type": "decimal",
      "default": 0
    },
    "tax": {
      "type": "relation",
      "relation": "oneToOne",
      "target": "api::tex.tex"
    },
    "taxAmount": {
      "type": "decimal",
      "default": 0
    },
    "totalNetto": {
      "type": "decimal",
      "default": 0
    }
  }
}
